fast_diff_match_patch.cpython-312-x86_64-linux-gnu.so
tests/test_match.py
tests/__init__.py
tests/test_diff.py
fast_diff_match_patch-2.1.0.dist-info/LICENSE
fast_diff_match_patch-2.1.0.dist-info/RECORD
fast_diff_match_patch-2.1.0.dist-info/top_level.txt
fast_diff_match_patch-2.1.0.dist-info/WHEEL
fast_diff_match_patch-2.1.0.dist-info/METADATA
