Metadata-Version: 2.1
Name: fast-diff-match-patch
Version: 2.1.0
Summary: Packages the C++ implementation of google-diff-match-patch for Python for fast byte and string diffs.
Home-page: https://github.com/JoshData/fast_diff_match_patch
Author: Joshua Tauberer
Author-email: jt@occams.info
License: Apache License 2.0
Keywords: diff compare Google match patch diff_match_patch native fast
Classifier: Programming Language :: Python :: 3
Classifier: Programming Language :: Python :: 3.6
Classifier: Programming Language :: Python :: 3.7
Classifier: Programming Language :: Python :: 3.8
Classifier: Programming Language :: Python :: 3.9
Classifier: Programming Language :: Python :: 3.10
Classifier: Programming Language :: Python :: 3.11
Classifier: Programming Language :: Python :: 3.12
License-File: LICENSE
